rzk/__init__.py
rzk/generate_svgs.py
mkdocs_plugin_rzk-0.1.4.dist-info/METADATA
mkdocs_plugin_rzk-0.1.4.dist-info/WHEEL
mkdocs_plugin_rzk-0.1.4.dist-info/entry_points.txt
mkdocs_plugin_rzk-0.1.4.dist-info/top_level.txt
mkdocs_plugin_rzk-0.1.4.dist-info/RECORD
