Metadata-Version: 2.1
Name: mkdocs-plugin-rzk
Version: 0.1.4
Summary: A MkDocs plugin for Literate Rzk
Author: Abdelrahman Abounegm
Author-email: a.abounegm@innopolis.university
License: MIT
Project-URL: Source, https://github.com/rzk-lang/mkdocs-plugin-rzk
Project-URL: Release notes, https://github.com/rzk-lang/mkdocs-plugin-rzk/blob/master/CHANGELOG.md
Project-URL: Tracker, https://github.com/rzk-lang/mkdocs-plugin-rzk/issues
Keywords: mkdocs
Requires-Dist: mkdocs >=1.4.0
